app/__init__.py
app/__main__.py
app/clients/__init__.py
app/clients/github.py
app/clients/kube.py
app/common/__init__.py
app/common/config_files.py
app/common/file_check.py
app/common/file_operations.py
app/common/versions.py
app/config/__init__.py
app/config/args.py
app/config/bootstrap.py
app/config/data/default_apps.yaml
app/config/log_settings.py
app/config/os_envs.py
app/endpoints/__init__.py
app/endpoints/health.py
app/endpoints/metrics.py
app/endpoints/root.py
app/libs/__init__.py
app/libs/github_lib.py
app/libs/kube_lib.py
app/monitoring/__init__.py
app/monitoring/metrics.py
app/monitoring/registry.py
app/web/__init__.py
app/web/server.py
app/web/workflows.py
app/workflows/__init__.py
app/workflows/outputs.py
app/workflows/pods_inventory.py
app/workflows/process.py
kube_inventory-1.0.1.dist-info/METADATA
kube_inventory-1.0.1.dist-info/WHEEL
kube_inventory-1.0.1.dist-info/entry_points.txt
kube_inventory-1.0.1.dist-info/licenses/LICENSE.md
kube_inventory-1.0.1.dist-info/RECORD
