Metadata-Version: 2.4
Name: kube-inventory
Version: 1.0.1
Summary: Inventory of softwares running in a Kubernetes cluster
License: MIT
License-File: LICENSE.md
Author: Emerson Candido
Author-email: emerson.candido@live.com
Requires-Python: >=3.13,<4.0
Classifier: License :: OSI Approved :: MIT License
Classifier: Programming Language :: Python :: 3
Classifier: Programming Language :: Python :: 3.13
Classifier: Programming Language :: Python :: 3.14
Requires-Dist: flask (==3.1.2)
Requires-Dist: gunicorn (==23.0.0)
Requires-Dist: kubernetes (==34.1.0)
Requires-Dist: poetry-core (>=2.2.1,<3.0.0)
Requires-Dist: prometheus-client (==0.23.1)
Requires-Dist: psutil (==7.1.0)
Requires-Dist: python-dotenv (==1.1.1)
Requires-Dist: requests (==2.32.4)
